runcli/__init__.py
runcli/runcli.py
runcli/test_runcli.py
runcli/utils.py
runcli-0.0.1.data/scripts/run
runcli-0.0.1.dist-info/DESCRIPTION.rst
runcli-0.0.1.dist-info/METADATA
runcli-0.0.1.dist-info/RECORD
runcli-0.0.1.dist-info/WHEEL
runcli-0.0.1.dist-info/metadata.json
runcli-0.0.1.dist-info/top_level.txt
tests/__init__.py
tests/test_endtoend.py
