Metadata-Version: 2.0
Name: runcli
Version: 0.0.1
Summary: Use Runfiles in your projects.
Home-page: https://github.com/nalourie/runcli
Author: Nicholas Lourie
Author-email: UNKNOWN
License: MIT
Keywords: development
Platform: UNKNOWN
Classifier: Development Status :: 3 - Alpha
Classifier: Intended Audience :: Developers
Classifier: License :: OSI Approved :: MIT License
Classifier: Programming Language :: Python :: 2
Classifier: Programming Language :: Python :: 3
